{
  "updated_at": "2026-06-18T23:27:29Z",
  "score": 0,
  "action": "正常持有",
  "base_position": 80,
  "suggested_position": 80,
  "signals": {
    "zijin_weakness": false,
    "gdx_weakness": false,
    "copper_breakdown": false,
    "divergence": false,
    "risk_spike": false
  },
  "raw": {
    "zijin": 29.69,
    "gold": 4213.4,
    "gdx": 82.51,
    "copper": 6.3685,
    "vix": 16.4,
    "zijin_gold_ratio": 0.007047,
    "gdx_gold_ratio": 0.019583,
    "copper_gold_ratio": 0.001511,
    "zijin_gold_ratio_ma20": 0.006894,
    "gdx_gold_ratio_ma20": 0.01911,
    "copper_gold_ratio_ma20": 0.001463,
    "gold_ma20": 4375.21,
    "gdx_ma20": 83.64
  },
  "history": [
    {
      "date": "2026-05-08",
      "score": 0
    },
    {
      "date": "2026-05-11",
      "score": 1
    },
    {
      "date": "2026-05-12",
      "score": 0
    },
    {
      "date": "2026-05-13",
      "score": 0
    },
    {
      "date": "2026-05-14",
      "score": 1
    },
    {
      "date": "2026-05-15",
      "score": 2
    },
    {
      "date": "2026-05-18",
      "score": 2
    },
    {
      "date": "2026-05-19",
      "score": 2
    },
    {
      "date": "2026-05-20",
      "score": 2
    },
    {
      "date": "2026-05-21",
      "score": 2
    },
    {
      "date": "2026-05-22",
      "score": 2
    },
    {
      "date": "2026-05-25",
      "score": 2
    },
    {
      "date": "2026-05-26",
      "score": 0
    },
    {
      "date": "2026-05-27",
      "score": 2
    },
    {
      "date": "2026-05-28",
      "score": 2
    },
    {
      "date": "2026-05-29",
      "score": 1
    },
    {
      "date": "2026-06-01",
      "score": 2
    },
    {
      "date": "2026-06-02",
      "score": 1
    },
    {
      "date": "2026-06-03",
      "score": 1
    },
    {
      "date": "2026-06-04",
      "score": 2
    },
    {
      "date": "2026-06-05",
      "score": 2
    },
    {
      "date": "2026-06-08",
      "score": 2
    },
    {
      "date": "2026-06-09",
      "score": 2
    },
    {
      "date": "2026-06-10",
      "score": 2
    },
    {
      "date": "2026-06-11",
      "score": 1
    },
    {
      "date": "2026-06-12",
      "score": 0
    },
    {
      "date": "2026-06-15",
      "score": 0
    },
    {
      "date": "2026-06-16",
      "score": 0
    },
    {
      "date": "2026-06-17",
      "score": 0
    },
    {
      "date": "2026-06-18",
      "score": 0
    }
  ]
}